{
  "generated_at": "2026-06-23T16:33:12.460Z",
  "services": {
    "marketing": {
      "status": "down",
      "latency_ms": 0,
      "checked_at": "2026-06-23T16:33:12.460Z",
      "uptime_24h": 0,
      "uptime_90d": 0
    },
    "api": {
      "status": "up",
      "latency_ms": 0,
      "checked_at": "2026-06-23T16:33:13.028Z",
      "uptime_24h": 100,
      "uptime_90d": 100
    },
    "db": {
      "status": "up",
      "latency_ms": 172,
      "checked_at": "2026-06-23T16:33:12.971Z",
      "uptime_24h": 90.91,
      "uptime_90d": 94.71
    },
    "scribe": {
      "status": "up",
      "latency_ms": 960,
      "checked_at": "2026-06-23T16:33:15.297Z",
      "uptime_24h": 100,
      "uptime_90d": 99.78
    },
    "exports": {
      "status": "up",
      "latency_ms": 292,
      "checked_at": "2026-06-23T16:33:14.970Z",
      "uptime_24h": 100,
      "uptime_90d": 100
    },
    "auth": {
      "status": "up",
      "latency_ms": 152,
      "checked_at": "2026-06-23T16:33:12.967Z",
      "uptime_24h": 100,
      "uptime_90d": 100
    }
  }
}
