{
  "generated_at": "2026-07-10T13:23:27.233Z",
  "services": {
    "marketing": {
      "status": "down",
      "latency_ms": 0,
      "checked_at": "2026-07-10T13:23:27.233Z",
      "maintenance": true,
      "uptime_24h": 0,
      "uptime_90d": 0
    },
    "api": {
      "status": "up",
      "latency_ms": 0,
      "checked_at": "2026-07-10T13:23:27.455Z",
      "uptime_24h": 100,
      "uptime_90d": 100
    },
    "db": {
      "status": "degraded",
      "latency_ms": 1110,
      "checked_at": "2026-07-10T13:23:29.627Z",
      "uptime_24h": 85.71,
      "uptime_90d": 94.55
    },
    "scribe": {
      "status": "up",
      "latency_ms": 936,
      "checked_at": "2026-07-10T13:23:28.503Z",
      "uptime_24h": 100,
      "uptime_90d": 99.72
    },
    "exports": {
      "status": "up",
      "latency_ms": 297,
      "checked_at": "2026-07-10T13:23:29.137Z",
      "uptime_24h": 100,
      "uptime_90d": 100
    },
    "auth": {
      "status": "up",
      "latency_ms": 614,
      "checked_at": "2026-07-10T13:23:29.211Z",
      "uptime_24h": 100,
      "uptime_90d": 99.92
    }
  }
}
