{
  "generated_at": "2026-07-18T07:08:26.593Z",
  "services": {
    "marketing": {
      "status": "down",
      "latency_ms": 0,
      "checked_at": "2026-07-18T07:08:26.593Z",
      "maintenance": true,
      "uptime_24h": 0,
      "uptime_90d": 0
    },
    "api": {
      "status": "up",
      "latency_ms": 0,
      "checked_at": "2026-07-18T07:08:28.250Z",
      "uptime_24h": 100,
      "uptime_90d": 100
    },
    "db": {
      "status": "up",
      "latency_ms": 194,
      "checked_at": "2026-07-18T07:08:28.354Z",
      "uptime_24h": 100,
      "uptime_90d": 95.07
    },
    "scribe": {
      "status": "up",
      "latency_ms": 779,
      "checked_at": "2026-07-18T07:08:27.866Z",
      "uptime_24h": 100,
      "uptime_90d": 99.77
    },
    "exports": {
      "status": "up",
      "latency_ms": 273,
      "checked_at": "2026-07-18T07:08:28.701Z",
      "uptime_24h": 100,
      "uptime_90d": 100
    },
    "auth": {
      "status": "up",
      "latency_ms": 179,
      "checked_at": "2026-07-18T07:08:28.269Z",
      "uptime_24h": 100,
      "uptime_90d": 99.94
    }
  }
}
